hydra_yaml_lsp/__init__.py
hydra_yaml_lsp/__main__.py
hydra_yaml_lsp/constants.py
hydra_yaml_lsp/py.typed
hydra_yaml_lsp/server.py
hydra_yaml_lsp/utils.py
hydra_yaml_lsp/completions/__init__.py
hydra_yaml_lsp/completions/callable_arg.py
hydra_yaml_lsp/completions/import_path.py
hydra_yaml_lsp/completions/provider.py
hydra_yaml_lsp/completions/special_key.py
hydra_yaml_lsp/completions/special_key_value.py
hydra_yaml_lsp/completions/utils.py
hydra_yaml_lsp/core/__init__.py
hydra_yaml_lsp/core/detections/__init__.py
hydra_yaml_lsp/core/detections/hydra_package.py
hydra_yaml_lsp/core/detections/hydra_target.py
hydra_yaml_lsp/core/detections/interpolation.py
hydra_yaml_lsp/core/detections/special_key.py
hydra_yaml_lsp/core/lint/__init__.py
hydra_yaml_lsp/core/lint/message.py
hydra_yaml_lsp/core/lint/yaml_validator.py
hydra_yaml_lsp/definitions/__init__.py
hydra_yaml_lsp/diagnostics/__init__.py
hydra_yaml_lsp/diagnostics/provider.py
hydra_yaml_lsp/diagnostics/utils.py
hydra_yaml_lsp/diagnostics/yaml.py
hydra_yaml_lsp/semantic_tokens/__init__.py
hydra_yaml_lsp/semantic_tokens/builder.py
hydra_yaml_lsp/semantic_tokens/provider.py
hydra_yaml_lsp-0.1.1.dist-info/METADATA
hydra_yaml_lsp-0.1.1.dist-info/WHEEL
hydra_yaml_lsp-0.1.1.dist-info/RECORD
