Metadata-Version: 2.4
Name: hydra-yaml-lsp
Version: 0.1.1
Summary: Language Server Protocol implementation for Hydra YAML configuration files
Project-URL: Repository, https://github.com/Geson-anko/python-hydra-yaml
Project-URL: Issues, https://github.com/Geson-anko/python-hydra-yaml/issues
License-Expression: MIT
Keywords: autocomplete,completion,configuration,editor,hydra,intellisense,language-server,language-server-protocol,lsp,vscode,yaml
Classifier: Development Status :: 3 - Alpha
Classifier: Environment :: Plugins
Classifier: Intended Audience :: Developers
Classifier: License :: OSI Approved :: MIT License
Classifier: Programming Language :: Python
Classifier: Programming Language :: Python :: 3
Classifier: Programming Language :: Python :: 3.12
Classifier: Programming Language :: Python :: 3.13
Classifier: Programming Language :: Python :: 3.14
Classifier: Topic :: Software Development
Classifier: Topic :: Software Development :: Libraries :: Python Modules
Classifier: Topic :: Text Editors
Classifier: Topic :: Text Editors :: Integrated Development Environments (IDE)
Classifier: Topic :: Text Processing :: Markup
Classifier: Typing :: Typed
Requires-Python: >=3.12
Requires-Dist: hydra-core>=1.3.2
Requires-Dist: pygls>=1.3.1
Requires-Dist: ruamel-yaml>=0.18.10
